LICENSE
README.md
setup.py
API/__init__.py
API/encrypt.py
API/binance/__init__.py
API/binance/config_template.py
API/binance/private_access.py
API/binance/public_access.py
kiwano_portfolio.egg-info/PKG-INFO
kiwano_portfolio.egg-info/SOURCES.txt
kiwano_portfolio.egg-info/dependency_links.txt
kiwano_portfolio.egg-info/top_level.txt
model/__init__.py
model/metrics.py
model/model_utils.py
model/plot_functions.py
model/portfolio.py
model/strategy.py
strategy/__init__.py
strategy/generic_strategies.py
strategy/run_strategy.py
tests/__init__.py
tests/test_file.py