Metadata-Version: 2.1
Name: kiwano-portfolio
Version: 1.0.1
Summary: This is a python package to backtest, livetest and livetrade your strategies on crypto currencies.
Home-page: https://github.com/onekiwano/kiwano_portfolio
Author: Luca Herranz-Celotti
Author-email: luca.herrtti@gmail.com
License: Apache License
Classifier: Development Status :: 3 - Alpha
Classifier: Programming Language :: Python :: 3 :: Only
Classifier: License :: OSI Approved :: MIT License
Classifier: Operating System :: OS Independent
License-File: LICENSE
